agent/__init__.py
agent/__main__.py
agent/cli.py
agent/commit.py
agent/llm.py
git_commit_agent-0.0.1.dist-info/METADATA
git_commit_agent-0.0.1.dist-info/WHEEL
git_commit_agent-0.0.1.dist-info/entry_points.txt
git_commit_agent-0.0.1.dist-info/licenses/LICENSE
git_commit_agent-0.0.1.dist-info/RECORD
